LICENSE
MANIFEST.in
README.rst
integration_test_lite.py
integration_test_post.py
setup.py
test.py
doc/SMS_Gate_API_LITE_20-2.pdf
doc/SMS_Gate_API_POST_20-1.pdf
smssluzbacz_api/__init__.py
smssluzbacz_api/lite.py
smssluzbacz_api/post.py
smssluzbacz_api.egg-info/PKG-INFO
smssluzbacz_api.egg-info/SOURCES.txt
smssluzbacz_api.egg-info/dependency_links.txt
smssluzbacz_api.egg-info/requires.txt
smssluzbacz_api.egg-info/top_level.txt
smssluzbacz_api/test/__init__.py
smssluzbacz_api/test/test_lite_api.py
smssluzbacz_api/test/test_post_api.py