Metadata-Version: 1.1
Name: smssluzbacz-api
Version: 1.1
Summary: api library for sending SMS (shor text message) via sms.sluzba.cz service
Home-page: http://www.codescale.net/en/community#smssluzbacz-api
Author: Vladimír Gorej, Jozef Ševčík
Author-email: info@codescale.net
License: BSD
Download-URL: https://github.com/jsk/python-smssluzbacz-api/tarball/master
Keywords: sms api
Platform: any
Classifier: Development Status :: 5 - Production/Stable
Classifier: Environment :: Console
Classifier: Environment :: Web Environment
Classifier: Intended Audience :: Developers
Classifier: Intended Audience :: System Administrators
Classifier: License :: OSI Approved :: BSD License
Classifier: Operating System :: OS Independent
Classifier: Programming Language :: Python
Classifier: Topic :: Utilities
